python_starter/__init__.py
python_starter/src/__init__.py
python_starter/src/cli.py
python_starter/src/actions/__init__.py
python_starter/src/actions/setup_project.py
python_starter/src/actions/workflow.py
python_starter/src/templates/__init__.py
python_starter/src/templates/const.py
py_starter_auto_template-0.0.2.dist-info/LICENSE
py_starter_auto_template-0.0.2.dist-info/METADATA
py_starter_auto_template-0.0.2.dist-info/WHEEL
py_starter_auto_template-0.0.2.dist-info/entry_points.txt
py_starter_auto_template-0.0.2.dist-info/top_level.txt
py_starter_auto_template-0.0.2.dist-info/RECORD
