Metadata-Version: 2.1
Name: py_starter_auto_template
Version: 0.0.2
Summary: Creating a template Python package with a CLI interface. 
Author: Shaofeng Kang
Author-email: robkangshaofeng@gmail.com
Keywords: python starter template cli version control python-starter python-starter-template python-starter-cli
Requires-Python: >3.11
License-File: LICENSE
Requires-Dist: bump2version ==1.0.1
Requires-Dist: setuptools ==69.0.3
